1/three_to_8_decoder.v
`timescale 1ns / 1ps
//////////////////////////////////////////////////////////////////////////////////
// Company: 
// Engineer: 
// 
// Create Date:    12:54:00 01/15/2023 
// Design Name: 
// Module Name:    three_to_8_decoder 
// Project Name: 
// Target Devices: 
// Tool versions: 
// Description: 
//
// Dependencies: 
//
// Revision: 
// Revision 0.01 - File Created
// Additional Comments: 
//
//////////////////////////////////////////////////////////////////////////////////
module threee_to_8_decoder( in,out, e);


input [2:0] in;
input e;
output reg [7:0] out;

always @* 
  begin 
    if(e)
     begin
      case (in)
        000 : out = 10000000;
        001 : out = 01000000;
        010 : out = 00100000;
        011 : out = 00010000;
        100 : out = 00001000;
        101 : out = 00000100;
        110 : out = 00000010;
        default : out = 00000001;
      endcase
     end
     else
      begin
        out = 00000000;
      end
  end
  



endmodule

1/test_3_to_8.v
`timescale 1ns / 1ps
`include "three_to_8_decoder.v"
//////////////////////////////////////////////////////////////////////////////////
// Company: 
// Engineer: 
// 
// Create Date:    13:23:46 01/15/2023 
// Design Name: 
// Module Name:    test_3_to_8 
// Project Name: 
// Target Devices: 
// Tool versions: 
// Description: 
//
// Dependencies: 
//
// Revision: 
// Revision 0.01 - File Created
// Additional Comments: 
//
//////////////////////////////////////////////////////////////////////////////////
module test_3_to_8;

reg [2:0] inp;
reg en;
wire [7:0] outp;

threee_to_8_decoder uut(.in(inp), .out(outp), .e(en));
initial begin
      $dumpfile("test3to8.vcd");
      $dumpvars(0,test_3_to_8);
  inp = 000;
  en = 1;
end

initial begin
  #50 inp=001;
  #100 en=0;
  #200 en=1;
  inp=101;
  #100 inp=111;
  #50 inp=010;
  #50 inp=011;
  #50 inp=110;
end


endmodule

1/test3to8.vcd
$date
	Sun Jan 15 19:50:04 2023
$end
$version
	Icarus Verilog
$end
$timescale
	1ps
$end
$scope module test_3_to_8 $end
$var wire 8 ! outp [7:0] $end
$var reg 1 " en $end
$var reg 3 # inp [2:0] $end
$scope module uut $end
$var wire 1 " e $end
$var wire 3 $ in [2:0] $end
$var reg 8 % out [7:0] $end
$upscope $end
$upscope $end
$enddefinitions $end
$comment Show the parameter values. $end
$dumpall
$end
#0
$dumpvars
b10000000 %
b0 $
b0 #
1"
b10000000 !
$end
#50000
b1000000 !
b1000000 %
b1 #
b1 $
#150000
b0 !
b0 %
0"
#350000
b1 !
b1 %
b101 #
b101 $
1"
#450000
b111 #
b111 $
#500000
b10 #
b10 $
#550000
b11 #
b11 $
#600000
b110 #
b110 $
